videoscripy/__init__.py
videoscripy/videoscripy.py
VideoScripy-0.0.1.dist-info/LICENSE
VideoScripy-0.0.1.dist-info/METADATA
VideoScripy-0.0.1.dist-info/WHEEL
VideoScripy-0.0.1.dist-info/entry_points.txt
VideoScripy-0.0.1.dist-info/top_level.txt
VideoScripy-0.0.1.dist-info/RECORD
