Metadata-Version: 2.1
Name: VideoScripy
Version: 0.0.1
Summary: Collection of video processes such as Optimize, Upscale and Interpolation.
Author-email: luezhi <sunluezhi520@gmail.com>
Project-URL: Homepage, https://github.com/luewh/Video-Script
Project-URL: Issues, https://github.com/luewh/Video-Script/issues
Keywords: ffmpeg,upscale,interpolate,video process
Classifier: Programming Language :: Python :: 3
Classifier: License :: OSI Approved :: MIT License
Classifier: Operating System :: Microsoft :: Windows :: Windows 10
Classifier: Environment :: GPU :: NVIDIA CUDA
Requires-Python: >=3.10
License-File: LICENSE
Requires-Dist: psutil ==6.1.0
Requires-Dist: ffmpeg-python ==0.2.0
Requires-Dist: alive-progress ==3.2.0
